{
  "id": "docs",
  "name": "Documentation",
  "url": "https://docs.tensamin.net/",
  "checks": [
    {
      "t": "2026-02-06T14:10:55.892Z",
      "ok": true,
      "code": 200,
      "rt": 570
    },
    {
      "t": "2026-02-06T14:59:45.557Z",
      "ok": true,
      "code": 200,
      "rt": 496
    },
    {
      "t": "2026-02-06T15:51:32.604Z",
      "ok": true,
      "code": 200,
      "rt": 509
    },
    {
      "t": "2026-02-06T16:31:37.555Z",
      "ok": true,
      "code": 200,
      "rt": 501
    },
    {
      "t": "2026-02-06T17:23:59.738Z",
      "ok": true,
      "code": 200,
      "rt": 404
    },
    {
      "t": "2026-02-06T18:04:39.613Z",
      "ok": true,
      "code": 200,
      "rt": 397
    },
    {
      "t": "2026-02-06T19:05:04.639Z",
      "ok": true,
      "code": 200,
      "rt": 513
    },
    {
      "t": "2026-02-06T19:46:50.785Z",
      "ok": true,
      "code": 200,
      "rt": 534
    },
    {
      "t": "2026-02-06T20:16:41.337Z",
      "ok": true,
      "code": 200,
      "rt": 535
    },
    {
      "t": "2026-02-06T20:53:03.436Z",
      "ok": true,
      "code": 200,
      "rt": 526
    },
    {
      "t": "2026-02-06T21:24:35.416Z",
      "ok": true,
      "code": 200,
      "rt": 582
    },
    {
      "t": "2026-02-06T21:52:24.983Z",
      "ok": true,
      "code": 200,
      "rt": 536
    },
    {
      "t": "2026-02-06T22:14:53.501Z",
      "ok": true,
      "code": 200,
      "rt": 462
    },
    {
      "t": "2026-02-06T22:44:55.942Z",
      "ok": true,
      "code": 200,
      "rt": 442
    },
    {
      "t": "2026-02-06T23:01:11.687Z",
      "ok": true,
      "code": 200,
      "rt": 401
    },
    {
      "t": "2026-02-06T23:36:31.754Z",
      "ok": true,
      "code": 200,
      "rt": 599
    },
    {
      "t": "2026-02-06T23:55:46.316Z",
      "ok": true,
      "code": 200,
      "rt": 445
    },
    {
      "t": "2026-02-07T02:05:23.445Z",
      "ok": true,
      "code": 200,
      "rt": 397
    },
    {
      "t": "2026-02-07T04:14:44.434Z",
      "ok": true,
      "code": 200,
      "rt": 472
    },
    {
      "t": "2026-02-07T05:12:43.648Z",
      "ok": true,
      "code": 200,
      "rt": 347
    },
    {
      "t": "2026-02-07T05:57:20.626Z",
      "ok": true,
      "code": 200,
      "rt": 531
    },
    {
      "t": "2026-02-07T06:51:03.553Z",
      "ok": true,
      "code": 200,
      "rt": 522
    },
    {
      "t": "2026-02-07T07:23:01.434Z",
      "ok": true,
      "code": 200,
      "rt": 551
    },
    {
      "t": "2026-02-07T07:49:51.102Z",
      "ok": true,
      "code": 200,
      "rt": 546
    },
    {
      "t": "2026-02-07T08:14:23.069Z",
      "ok": true,
      "code": 200,
      "rt": 500
    },
    {
      "t": "2026-02-07T08:50:10.676Z",
      "ok": true,
      "code": 200,
      "rt": 381
    },
    {
      "t": "2026-02-07T09:17:11.338Z",
      "ok": true,
      "code": 200,
      "rt": 395
    },
    {
      "t": "2026-02-07T09:49:00.660Z",
      "ok": true,
      "code": 200,
      "rt": 374
    },
    {
      "t": "2026-02-07T10:01:09.886Z",
      "ok": true,
      "code": 200,
      "rt": 440
    },
    {
      "t": "2026-02-07T10:39:22.285Z",
      "ok": true,
      "code": 200,
      "rt": 479
    },
    {
      "t": "2026-02-07T10:58:37.506Z",
      "ok": true,
      "code": 200,
      "rt": 581
    },
    {
      "t": "2026-02-07T11:29:19.132Z",
      "ok": true,
      "code": 200,
      "rt": 536
    },
    {
      "t": "2026-02-07T11:47:55.056Z",
      "ok": true,
      "code": 200,
      "rt": 445
    },
    {
      "t": "2026-02-07T11:58:34.587Z",
      "ok": true,
      "code": 200,
      "rt": 562
    },
    {
      "t": "2026-02-07T13:07:40.698Z",
      "ok": true,
      "code": 200,
      "rt": 411
    },
    {
      "t": "2026-02-07T13:52:11.736Z",
      "ok": true,
      "code": 200,
      "rt": 417
    },
    {
      "t": "2026-02-07T14:17:43.617Z",
      "ok": true,
      "code": 200,
      "rt": 605
    },
    {
      "t": "2026-02-07T14:47:32.872Z",
      "ok": true,
      "code": 200,
      "rt": 450
    },
    {
      "t": "2026-02-07T15:11:08.673Z",
      "ok": true,
      "code": 200,
      "rt": 406
    },
    {
      "t": "2026-02-07T15:41:18.734Z",
      "ok": true,
      "code": 200,
      "rt": 481
    },
    {
      "t": "2026-02-07T15:58:37.023Z",
      "ok": true,
      "code": 200,
      "rt": 446
    },
    {
      "t": "2026-02-07T16:40:59.600Z",
      "ok": true,
      "code": 200,
      "rt": 531
    },
    {
      "t": "2026-02-07T17:02:43.225Z",
      "ok": true,
      "code": 200,
      "rt": 365
    },
    {
      "t": "2026-02-07T17:36:50.809Z",
      "ok": true,
      "code": 200,
      "rt": 593
    },
    {
      "t": "2026-02-07T17:56:00.244Z",
      "ok": true,
      "code": 200,
      "rt": 476
    },
    {
      "t": "2026-02-07T18:37:59.122Z",
      "ok": true,
      "code": 200,
      "rt": 422
    },
    {
      "t": "2026-02-07T19:03:41.364Z",
      "ok": true,
      "code": 200,
      "rt": 441
    },
    {
      "t": "2026-02-07T19:33:46.766Z",
      "ok": true,
      "code": 200,
      "rt": 534
    },
    {
      "t": "2026-02-07T19:49:57.107Z",
      "ok": true,
      "code": 200,
      "rt": 449
    },
    {
      "t": "2026-02-07T19:59:48.467Z",
      "ok": true,
      "code": 200,
      "rt": 480
    },
    {
      "t": "2026-02-07T20:38:55.670Z",
      "ok": true,
      "code": 200,
      "rt": 533
    },
    {
      "t": "2026-02-07T20:58:43.130Z",
      "ok": true,
      "code": 200,
      "rt": 489
    },
    {
      "t": "2026-02-07T21:35:28.730Z",
      "ok": true,
      "code": 200,
      "rt": 562
    },
    {
      "t": "2026-02-07T21:55:08.464Z",
      "ok": true,
      "code": 200,
      "rt": 393
    },
    {
      "t": "2026-02-07T22:24:51.214Z",
      "ok": true,
      "code": 200,
      "rt": 520
    },
    {
      "t": "2026-02-07T22:53:23.555Z",
      "ok": true,
      "code": 200,
      "rt": 454
    },
    {
      "t": "2026-02-07T23:24:37.351Z",
      "ok": true,
      "code": 200,
      "rt": 589
    },
    {
      "t": "2026-02-07T23:55:01.291Z",
      "ok": true,
      "code": 200,
      "rt": 550
    },
    {
      "t": "2026-02-08T02:28:40.792Z",
      "ok": true,
      "code": 200,
      "rt": 474
    },
    {
      "t": "2026-02-08T04:52:21.307Z",
      "ok": true,
      "code": 200,
      "rt": 567
    },
    {
      "t": "2026-02-08T05:56:09.366Z",
      "ok": true,
      "code": 200,
      "rt": 543
    },
    {
      "t": "2026-02-08T06:52:57.770Z",
      "ok": true,
      "code": 200,
      "rt": 374
    },
    {
      "t": "2026-02-08T07:34:48.545Z",
      "ok": true,
      "code": 200,
      "rt": 411
    },
    {
      "t": "2026-02-08T07:59:32.964Z",
      "ok": true,
      "code": 200,
      "rt": 449
    },
    {
      "t": "2026-02-08T08:44:58.134Z",
      "ok": true,
      "code": 200,
      "rt": 532
    },
    {
      "t": "2026-02-08T09:15:33.050Z",
      "ok": true,
      "code": 200,
      "rt": 433
    },
    {
      "t": "2026-02-08T09:47:26.910Z",
      "ok": true,
      "code": 200,
      "rt": 532
    },
    {
      "t": "2026-02-08T10:00:57.024Z",
      "ok": true,
      "code": 200,
      "rt": 372
    },
    {
      "t": "2026-02-08T10:40:16.161Z",
      "ok": true,
      "code": 200,
      "rt": 526
    },
    {
      "t": "2026-02-08T11:00:39.612Z",
      "ok": true,
      "code": 200,
      "rt": 451
    },
    {
      "t": "2026-02-08T11:32:05.410Z",
      "ok": true,
      "code": 200,
      "rt": 400
    },
    {
      "t": "2026-02-08T11:49:40.306Z",
      "ok": true,
      "code": 200,
      "rt": 499
    },
    {
      "t": "2026-02-08T12:00:25.796Z",
      "ok": true,
      "code": 200,
      "rt": 561
    },
    {
      "t": "2026-02-08T13:09:30.778Z",
      "ok": true,
      "code": 200,
      "rt": 446
    },
    {
      "t": "2026-02-08T13:53:10.699Z",
      "ok": true,
      "code": 200,
      "rt": 550
    }
  ]
}