{
  "id": "omega",
  "name": "Omega",
  "url": "https://omega.tensamin.net/",
  "checks": [
    {
      "t": "2026-03-11T06:08:44.443Z",
      "ok": true,
      "code": 200,
      "rt": 909
    },
    {
      "t": "2026-03-11T07:10:41.360Z",
      "ok": true,
      "code": 200,
      "rt": 1198
    },
    {
      "t": "2026-03-11T07:54:55.612Z",
      "ok": true,
      "code": 200,
      "rt": 1013
    },
    {
      "t": "2026-03-11T08:39:45.276Z",
      "ok": true,
      "code": 200,
      "rt": 862
    },
    {
      "t": "2026-03-11T09:26:39.560Z",
      "ok": true,
      "code": 200,
      "rt": 1350
    },
    {
      "t": "2026-03-11T10:07:06.297Z",
      "ok": true,
      "code": 200,
      "rt": 980
    },
    {
      "t": "2026-03-11T10:58:36.418Z",
      "ok": true,
      "code": 200,
      "rt": 1213
    },
    {
      "t": "2026-03-11T11:40:30.121Z",
      "ok": true,
      "code": 200,
      "rt": 1206
    },
    {
      "t": "2026-03-11T12:01:27.925Z",
      "ok": true,
      "code": 200,
      "rt": 1188
    },
    {
      "t": "2026-03-11T13:22:44.266Z",
      "ok": true,
      "code": 200,
      "rt": 1122
    },
    {
      "t": "2026-03-11T14:14:36.873Z",
      "ok": true,
      "code": 200,
      "rt": 965
    },
    {
      "t": "2026-03-11T15:07:43.555Z",
      "ok": true,
      "code": 200,
      "rt": 899
    },
    {
      "t": "2026-03-11T16:00:33.712Z",
      "ok": true,
      "code": 200,
      "rt": 1199
    },
    {
      "t": "2026-03-11T17:03:29.455Z",
      "ok": true,
      "code": 200,
      "rt": 792
    },
    {
      "t": "2026-03-11T17:57:51.457Z",
      "ok": true,
      "code": 200,
      "rt": 1203
    },
    {
      "t": "2026-03-11T19:01:25.704Z",
      "ok": true,
      "code": 200,
      "rt": 920
    },
    {
      "t": "2026-03-11T19:46:17.325Z",
      "ok": true,
      "code": 200,
      "rt": 916
    },
    {
      "t": "2026-03-11T20:17:43.470Z",
      "ok": true,
      "code": 200,
      "rt": 1160
    },
    {
      "t": "2026-03-11T20:52:26.609Z",
      "ok": true,
      "code": 200,
      "rt": 896
    },
    {
      "t": "2026-03-11T21:24:53.346Z",
      "ok": true,
      "code": 200,
      "rt": 826
    },
    {
      "t": "2026-03-11T21:54:17.475Z",
      "ok": true,
      "code": 200,
      "rt": 891
    },
    {
      "t": "2026-03-11T22:23:44.443Z",
      "ok": true,
      "code": 200,
      "rt": 1178
    },
    {
      "t": "2026-03-11T22:48:23.074Z",
      "ok": true,
      "code": 200,
      "rt": 1155
    },
    {
      "t": "2026-03-11T23:12:19.530Z",
      "ok": true,
      "code": 200,
      "rt": 1378
    },
    {
      "t": "2026-03-11T23:42:27.817Z",
      "ok": true,
      "code": 200,
      "rt": 1375
    },
    {
      "t": "2026-03-11T23:59:41.344Z",
      "ok": true,
      "code": 200,
      "rt": 906
    },
    {
      "t": "2026-03-12T02:49:57.215Z",
      "ok": true,
      "code": 200,
      "rt": 1134
    },
    {
      "t": "2026-03-12T04:28:00.968Z",
      "ok": true,
      "code": 200,
      "rt": 959
    },
    {
      "t": "2026-03-12T06:31:57.248Z",
      "ok": true,
      "code": 200,
      "rt": 877
    },
    {
      "t": "2026-03-12T07:30:32.319Z",
      "ok": true,
      "code": 200,
      "rt": 962
    },
    {
      "t": "2026-03-12T08:03:36.119Z",
      "ok": true,
      "code": 200,
      "rt": 888
    },
    {
      "t": "2026-03-12T08:58:09.308Z",
      "ok": true,
      "code": 200,
      "rt": 1149
    },
    {
      "t": "2026-03-12T09:53:25.458Z",
      "ok": true,
      "code": 200,
      "rt": 1161
    },
    {
      "t": "2026-03-12T10:33:26.901Z",
      "ok": true,
      "code": 200,
      "rt": 1180
    },
    {
      "t": "2026-03-12T11:08:53.772Z",
      "ok": true,
      "code": 200,
      "rt": 1212
    },
    {
      "t": "2026-03-12T11:43:33.995Z",
      "ok": true,
      "code": 200,
      "rt": 953
    },
    {
      "t": "2026-03-12T12:00:42.178Z",
      "ok": true,
      "code": 200,
      "rt": 884
    },
    {
      "t": "2026-03-12T13:22:38.095Z",
      "ok": true,
      "code": 200,
      "rt": 1180
    },
    {
      "t": "2026-03-12T14:12:30.954Z",
      "ok": true,
      "code": 200,
      "rt": 872
    },
    {
      "t": "2026-03-12T15:10:02.343Z",
      "ok": true,
      "code": 200,
      "rt": 1159
    },
    {
      "t": "2026-03-12T16:14:17.584Z",
      "ok": false,
      "code": 404,
      "rt": 0
    },
    {
      "t": "2026-03-12T17:12:33.557Z",
      "ok": false,
      "code": 404,
      "rt": 0
    },
    {
      "t": "2026-03-12T18:02:51.941Z",
      "ok": false,
      "code": 404,
      "rt": 0
    },
    {
      "t": "2026-03-12T19:07:06.848Z",
      "ok": false,
      "code": 404,
      "rt": 0
    },
    {
      "t": "2026-03-12T19:50:46.874Z",
      "ok": false,
      "code": 404,
      "rt": 0
    },
    {
      "t": "2026-03-12T20:20:33.257Z",
      "ok": false,
      "code": 404,
      "rt": 0
    },
    {
      "t": "2026-03-12T20:56:33.800Z",
      "ok": false,
      "code": 404,
      "rt": 0
    },
    {
      "t": "2026-03-12T21:36:40.069Z",
      "ok": false,
      "code": 404,
      "rt": 0
    },
    {
      "t": "2026-03-12T21:58:28.181Z",
      "ok": false,
      "code": 404,
      "rt": 0
    },
    {
      "t": "2026-03-12T22:35:06.356Z",
      "ok": false,
      "code": 404,
      "rt": 0
    },
    {
      "t": "2026-03-12T22:57:46.516Z",
      "ok": false,
      "code": 404,
      "rt": 0
    },
    {
      "t": "2026-03-12T23:34:49.932Z",
      "ok": false,
      "code": 404,
      "rt": 0
    },
    {
      "t": "2026-03-12T23:55:27.444Z",
      "ok": false,
      "code": 404,
      "rt": 0
    },
    {
      "t": "2026-03-13T02:05:35.620Z",
      "ok": false,
      "code": 404,
      "rt": 0
    },
    {
      "t": "2026-03-13T04:19:41.534Z",
      "ok": false,
      "code": 404,
      "rt": 0
    },
    {
      "t": "2026-03-13T05:29:47.205Z",
      "ok": false,
      "code": 404,
      "rt": 0
    }
  ]
}